mocap_kalman/__init__.py
mocap_kalman/axengine_1765472831_3155591704.py
mocap_kalman/floorPlane/__init__.py
mocap_kalman/floorPlane/ppl_floor_plane_root_adjustment.py
mocap_kalman/kalman/__init__.py
mocap_kalman/kalman/adapters/__init__.py
mocap_kalman/kalman/adapters/data_adapters.py
mocap_kalman/kalman/adapters/data_loaders.py
mocap_kalman/kalman/adapters/initializer.py
mocap_kalman/kalman/adapters/interfaces.py
mocap_kalman/kalman/adapters/observer_adapters.py
mocap_kalman/kalman/core/__init__.py
mocap_kalman/kalman/core/filter.py
mocap_kalman/kalman/core/interfaces.py
mocap_kalman/kalman/core/linalg.py
mocap_kalman/kalman/core/multimodal.py
mocap_kalman/kalman/dynamics/__init__.py
mocap_kalman/kalman/dynamics/contact_utils/HIK.py
mocap_kalman/kalman/dynamics/contact_utils/contact_setup.py
mocap_kalman/kalman/dynamics/contact_utils/contact_trajectories.py
mocap_kalman/kalman/dynamics/contact_utils/floot_plane_fit.py
mocap_kalman/kalman/dynamics/dynamics_rbdl.py
mocap_kalman/kalman/dynamics/interfaces.py
mocap_kalman/kalman/dynamics/joint_torques.py
mocap_kalman/kalman/initializer.py
mocap_kalman/kalman/initializers/__init__.py
mocap_kalman/kalman/initializers/interfaces.py
mocap_kalman/kalman/kalman_settings.yaml
mocap_kalman/kalman/kalman_settings_sdc.yaml
mocap_kalman/kalman/kalman_settings_sdc_gvhmr.yaml
mocap_kalman/kalman/kf_exports.py
mocap_kalman/kalman/kf_manager.py
mocap_kalman/kalman/kinematics/__init__.py
mocap_kalman/kalman/kinematics/biomechanics.py
mocap_kalman/kalman/kinematics/bone_structures.py
mocap_kalman/kalman/kinematics/initializer.py
mocap_kalman/kalman/kinematics/interfaces.py
mocap_kalman/kalman/kinematics/inverse_kinematics.py
mocap_kalman/kalman/kinematics/kinematic_structures.py
mocap_kalman/kalman/kinematics/offset_structures.py
mocap_kalman/kalman/kinematics/rbdl_base_kinematics.py
mocap_kalman/kalman/kinematics/rbdl_offset_kinematics.py
mocap_kalman/kalman/kinematics/smpl_base_kinematics.py
mocap_kalman-3.6.7.dist-info/METADATA
mocap_kalman-3.6.7.dist-info/WHEEL
mocap_kalman-3.6.7.dist-info/RECORD
