Metadata-Version: 2.1
Name: mocap-kalman
Version: 3.6.7
Summary: 
Keywords: MotionOps,Moveai
Author: move.ai
Author-email: info@move.ai
Requires-Python: >=3.10,<3.13
Classifier: Programming Language :: Python :: 3
Classifier: Programming Language :: Python :: 3.10
Classifier: Programming Language :: Python :: 3.11
Classifier: Programming Language :: Python :: 3.12
Requires-Dist: bpy (==4.0.0) ; python_version >= "3.10.dev0" and python_version < "3.11.dev0"
Requires-Dist: bpy (>=4.1.0,<5.0.0) ; python_version >= "3.11.dev0" and python_version < "3.12.dev0"
Requires-Dist: cvxopt (>=1.3.1,<2.0.0)
Requires-Dist: matplotlib (==3.7.1)
Requires-Dist: mocap-base (>=2.5.1,<3.0.0)
Requires-Dist: mocap-skeletal (>=2.1.0,<3.0.0)
Requires-Dist: mocap_settings (>=1.12.1,<2.0.0)
Requires-Dist: pandas (>=2.0.2,<3.0.0)
Requires-Dist: qpsolvers (>=3.4.0,<4.0.0)
Requires-Dist: rbdl (>=3.2.1,<4.0.0)
Requires-Dist: rbdlp (>=2.6.1,<3.0.0)
Requires-Dist: scikit-learn (>=1.3.1,<2.0.0)
Requires-Dist: tqdm (>=4.65.0,<5.0.0)
Requires-Dist: urdf-creator (>=1.0.0,<2.0.0)
